korexo_profile/__init__.py
korexo_profile/korexo.py
korexo_profile-0.7.dist-info/METADATA
korexo_profile-0.7.dist-info/WHEEL
korexo_profile-0.7.dist-info/top_level.txt
korexo_profile-0.7.dist-info/RECORD
