Metadata-Version: 2.1
Name: korexo-profile
Version: 0.7
Summary: Read KorEXO sonde profile CSV files
Home-page: https://gitlab.com/dew-waterscience/korexo_profile
Author: DEW Water Science (Kent Inverarity)
Author-email: kent.inverarity@sa.gov.au
License: All rights reserved
Keywords: science
Classifier: Programming Language :: Python :: 3
Requires-Dist: pandas
Requires-Dist: numpy
Requires-Dist: scipy
Requires-Dist: lasio
